annoworkapi/__init__.py
annoworkapi/__version__.py
annoworkapi/actual_working_time.py
annoworkapi/annofab.py
annoworkapi/api.py
annoworkapi/enums.py
annoworkapi/exceptions.py
annoworkapi/generated_api.py
annoworkapi/job.py
annoworkapi/py.typed
annoworkapi/resource.py
annoworkapi/schedule.py
annoworkapi/utils.py
annoworkapi/wrapper.py
annoworkapi-3.3.dist-info/LICENSE
annoworkapi-3.3.dist-info/METADATA
annoworkapi-3.3.dist-info/WHEEL
annoworkapi-3.3.dist-info/RECORD
