Metadata-Version: 2.1
Name: annoworkapi
Version: 3.3
Summary: Python Clinet Library of Annowork WebAPI
Home-page: https://github.com/kurusugawa-computer/annowork-api-python-client
License: MIT
Keywords: annowork,api
Author: Kurusugawa Computer Inc.
Requires-Python: >=3.9,<4.0
Classifier: Development Status :: 5 - Production/Stable
Classifier: Intended Audience :: Developers
Classifier: License :: OSI Approved :: MIT License
Classifier: Operating System :: OS Independent
Classifier: Programming Language :: Python :: 3
Classifier: Programming Language :: Python :: 3.9
Classifier: Programming Language :: Python :: 3.10
Classifier: Programming Language :: Python :: 3.11
Classifier: Programming Language :: Python :: 3.12
Classifier: Topic :: Utilities
Requires-Dist: backoff
Requires-Dist: requests
Project-URL: Repository, https://github.com/kurusugawa-computer/annowork-api-python-client
